qore_client/__init__.py
qore_client/auth.py
qore_client/client.py
qore_client/config.py
qore_client/settings.py
qore_client/_internal/__init__.py
qore_client/_internal/graph.py
qore_client/_internal/module.py
qore_client/_internal/nodes.py
qore_client/_internal/validators.py
qore_client/api/__init__.py
qore_client/api/drive.py
qore_client/api/file.py
qore_client/api/folder.py
qore_client/api/organization.py
qore_client/api/output_parser.py
qore_client/api/webhook.py
qore_client/api/workflow.py
qore_client/api/workspace.py
qore_client/models/__init__.py
qore_client/models/workflow.py
qore_client/models/workflow_models.py
qore_client-0.1.7.dist-info/METADATA
qore_client-0.1.7.dist-info/WHEEL
qore_client-0.1.7.dist-info/top_level.txt
qore_client-0.1.7.dist-info/RECORD
