Metadata-Version: 2.4
Name: qore-client
Version: 0.1.7
Summary: Qore Client
Author-email: dhlee <dhlee@quantit.com>, sic <shininchul@quantit.io>, 94wogus <94wogus@quantit.io>
Classifier: Programming Language :: Python :: 3
Classifier: License :: OSI Approved :: MIT License
Classifier: Operating System :: OS Independent
Requires-Python: >=3.8
Requires-Dist: requests>=2.28.0
Requires-Dist: types-requests>=2.28.0
Requires-Dist: python-dotenv>=1.0.1
Requires-Dist: boto3>=1.33.0
Requires-Dist: types-boto3>=1.0.0
Requires-Dist: pandas>=2.0.0
Requires-Dist: pyarrow>=17.0.0
Requires-Dist: build>=1.2.2.post1
Requires-Dist: pydantic>=2.10.6
Requires-Dist: ipython>=8.12.3
Requires-Dist: finter>=0.4.81
Requires-Dist: pyiceberg>=0.7.1
